g2py/__init__.py
g2py/engine.py
g2py/meta.py
g2py/plot.py
g2py/helper/__init__.py
g2py/helper/code.py
g2py/helper/file.py
g2py/helper/html.py
g2py/static/g2.min.js
g2py/templates/jupyter-lab.html
g2py/templates/notebook.html
g2py/templates/plot.html
g2py-1.0.0.dist-info/LICENSE
g2py-1.0.0.dist-info/METADATA
g2py-1.0.0.dist-info/WHEEL
g2py-1.0.0.dist-info/entry_points.txt
g2py-1.0.0.dist-info/top_level.txt
g2py-1.0.0.dist-info/RECORD
