Metadata-Version: 2.1
Name: g2py
Version: 1.0.0
Summary: 基于蚂蚁集团G2可视化引擎的Python数据可视化库
Home-page: https://github.com/g2py/g2py
Author: G2PY Development Team
Author-email: G2PY Development Team <admin@g2py.org>
Maintainer-email: G2PY Development Team <admin@g2py.org>
License: MIT
Project-URL: Homepage, https://github.com/g2py/g2py
Project-URL: Documentation, https://github.com/g2py/g2py/blob/main/README.md
Project-URL: Repository, https://github.com/g2py/g2py.git
Project-URL: Bug Reports, https://github.com/g2py/g2py/issues
Project-URL: Changelog, https://github.com/g2py/g2py/blob/main/CHANGELOG.md
Keywords: 数据可视化,图表,G2,AntV,Python,Jupyter,可视化
Classifier: Development Status :: 4 - Beta
Classifier: Intended Audience :: Developers
Classifier: Intended Audience :: Science/Research
Classifier: Intended Audience :: Education
Classifier: Topic :: Scientific/Engineering :: Visualization
Classifier: Topic :: Software Development :: Libraries :: Python Modules
Classifier: Topic :: Multimedia :: Graphics :: Graphics Conversion
Classifier: Programming Language :: Python :: 3
Classifier: Programming Language :: Python :: 3.11
Classifier: Programming Language :: Python :: 3.12
Classifier: Programming Language :: Python :: 3 :: Only
Classifier: Operating System :: OS Independent
Classifier: Operating System :: Microsoft :: Windows
Classifier: Operating System :: POSIX :: Linux
Classifier: Operating System :: MacOS
Classifier: Environment :: Web Environment
Classifier: Environment :: Console
Classifier: Framework :: Jupyter
Requires-Python: >=3.11
License-File: LICENSE
Requires-Dist: jinja2 (>=3.1.0)
Requires-Dist: simplejson (>=3.17.0)
Provides-Extra: dev
Requires-Dist: pytest (>=7.0.0) ; extra == 'dev'
Requires-Dist: pytest-cov (>=4.0.0) ; extra == 'dev'
Requires-Dist: black (>=23.0.0) ; extra == 'dev'
Requires-Dist: flake8 (>=6.0.0) ; extra == 'dev'
Requires-Dist: mypy (>=1.0.0) ; extra == 'dev'
Provides-Extra: jupyter
Requires-Dist: jupyter (>=1.0.0) ; extra == 'jupyter'
Requires-Dist: jupyterlab (>=3.0.0) ; extra == 'jupyter'
Requires-Dist: ipython (>=7.0.0) ; extra == 'jupyter'
